beschi/__init__.py
beschi/__main__.py
beschi/cli.py
beschi/protocol.py
beschi/writer.py
beschi/writers/__init__.py
beschi/writers/assemblyscript.py
beschi/writers/c.py
beschi/writers/csharp.py
beschi/writers/go.py
beschi/writers/rust.py
beschi/writers/swift.py
beschi/writers/typescript.py
beschi/writers/zig.py
beschi/writers/boilerplate/AssemblyScript.ts
beschi/writers/boilerplate/C.0.h
beschi/writers/boilerplate/C.1.h
beschi/writers/boilerplate/C.2.h
beschi/writers/boilerplate/CSharp.0.cs
beschi/writers/boilerplate/CSharp.1.cs
beschi/writers/boilerplate/Go.go
beschi/writers/boilerplate/Rust.rs
beschi/writers/boilerplate/Swift.0.swift
beschi/writers/boilerplate/Swift.1.swift
beschi/writers/boilerplate/TypeScript.ts
beschi/writers/boilerplate/Zig.zig
beschi-0.3.2.dist-info/LICENSE.txt
beschi-0.3.2.dist-info/METADATA
beschi-0.3.2.dist-info/WHEEL
beschi-0.3.2.dist-info/entry_points.txt
beschi-0.3.2.dist-info/top_level.txt
beschi-0.3.2.dist-info/RECORD
