Metadata-Version: 2.2
Name: beschi
Version: 0.3.2
Summary: bit-packing and unpacking code generator for C, C#, Go, Rust, Swift, TypeScript, AssemblyScript, and Zig
Home-page: https://github.com/sjml/beschi
Author: Shane Liesegang
License: MIT
Classifier: Development Status :: 4 - Beta
Classifier: Environment :: Console
Classifier: License :: OSI Approved :: MIT License
Classifier: Programming Language :: Python :: 3
Classifier: Programming Language :: Python :: 3.11
Classifier: Intended Audience :: Developers
Classifier: Topic :: Software Development :: Code Generators
License-File: LICENSE.txt
Provides-Extra: dev
Requires-Dist: pytest; extra == "dev"
Provides-Extra: publish
Requires-Dist: build; extra == "publish"
Requires-Dist: twine; extra == "publish"
Requires-Dist: setuptools; extra == "publish"
Dynamic: author
Dynamic: classifier
Dynamic: description
Dynamic: description-content-type
Dynamic: home-page
Dynamic: license
Dynamic: provides-extra
Dynamic: summary
